{
  "specs_html": "<table class=\"ks-table\">\n          <tbody><tr class=\"ks-table-row\">\n          <td class=\"ks-table-cell ks-table-header-cell\">Wing</td>\n        \n          <td class=\"ks-table-cell ks-table-header-cell\">Surface Area (cm^2)</td>\n        \n          <td class=\"ks-table-cell ks-table-header-cell\">Span</td>\n        \n          <td class=\"ks-table-cell ks-table-header-cell\">Aspect Ratio</td>\n        \n          <td class=\"ks-table-cell ks-table-header-cell\">Weight</td>\n        </tr><tr class=\"ks-table-row\">\n          <td class=\"ks-table-cell ks-table-header-cell\">Flow 600</td>\n        \n          <td class=\"ks-table-cell\">600</td>\n        \n        <td class=\"ks-table-cell\" data-unit-values=\"{&quot;0&quot;:&quot;31 &lt;sup&gt;15&lt;/sup&gt;⁄&lt;sub&gt;16&lt;/sub&gt;\\&quot;&quot;,&quot;1&quot;:&quot;812mm&quot;}\" data-unit-type=\"single\">\n          812mm\n        </td>\n      \n          <td class=\"ks-table-cell\">11</td>\n        \n        <td class=\"ks-table-cell\" data-unit-values=\"{&quot;0&quot;:&quot;1.68lb&quot;,&quot;1&quot;:&quot;0.76kg&quot;}\" data-unit-type=\"single\">\n          0.76kg\n        </td>\n      </tr><tr class=\"ks-table-row\">\n          <td class=\"ks-table-cell ks-table-header-cell\">Flow 800</td>\n        \n          <td class=\"ks-table-cell\">800</td>\n        \n        <td class=\"ks-table-cell\" data-unit-values=\"{&quot;0&quot;:&quot;36 &lt;sup&gt;15&lt;/sup&gt;⁄&lt;sub&gt;16&lt;/sub&gt;\\&quot;&quot;,&quot;1&quot;:&quot;938mm&quot;}\" data-unit-type=\"single\">\n          938mm\n        </td>\n      \n          <td class=\"ks-table-cell\">11</td>\n        \n        <td class=\"ks-table-cell\" data-unit-values=\"{&quot;0&quot;:&quot;2.07lb&quot;,&quot;1&quot;:&quot;0.94kg&quot;}\" data-unit-type=\"single\">\n          0.94kg\n        </td>\n      </tr><tr class=\"ks-table-row\">\n          <td class=\"ks-table-cell ks-table-header-cell\">Flow 1000</td>\n        \n          <td class=\"ks-table-cell\">1000</td>\n        \n        <td class=\"ks-table-cell\" data-unit-values=\"{&quot;0&quot;:&quot;41 &lt;sup&gt;5&lt;/sup&gt;⁄&lt;sub&gt;16&lt;/sub&gt;\\&quot;&quot;,&quot;1&quot;:&quot;1049mm&quot;}\" data-unit-type=\"single\">\n          1049mm\n        </td>\n      \n          <td class=\"ks-table-cell\">11</td>\n        \n        <td class=\"ks-table-cell\" data-unit-values=\"{&quot;0&quot;:&quot;2.47lb&quot;,&quot;1&quot;:&quot;1.12kg&quot;}\" data-unit-type=\"single\">\n          1.12kg\n        </td>\n      </tr></tbody>\n        </table>",
  "package_includes": "<p>One-Lock Flow Front Wing, Protective Cover, Replacement One-Lock Latch Kit</p>",
  "description_html": "",
  "description_html2": "",
  "slug": "one-lock-flow-front-wing",
  "url": "https://slingshotsports.com/en-eu/products/one-lock-flow-front-wing"
}